elmoclient/__init__.py
elmoclient/elmoprocessor.py
python_elmoclient-0.0.9.dist-info/licenses/LICENSE
python_elmoclient-0.0.9.dist-info/METADATA
python_elmoclient-0.0.9.dist-info/WHEEL
python_elmoclient-0.0.9.dist-info/top_level.txt
python_elmoclient-0.0.9.dist-info/zip-safe
python_elmoclient-0.0.9.dist-info/RECORD
